relaxed_types
