Metadata-Version: 1.1
Name: relaxed-types
Version: 1.0.1
Summary: relaxed_types
Home-page: https://github.com/Yipit/relaxed_types
Author: Yipit Coders
Author-email: coders@yipit.com
License: UNKNOWN
Platform: UNKNOWN
Classifier: Programming Language :: Python
